{
  "faction": "Monsters",
  "leader": "leaders_monsters_eredin_the_treacherous",
  "totalNumberOfCards": 40,
  "totalNumberOfHeros": 3,
  "totalNumberOfSoldiers": 33,
  "totalNumberOfSpecialCards": 4,
  "sumOfPowers": 157,
  "cards": [
    "special_horn",
    "special_horn_1",
    "special_decoy",
    "special_decoy_1",
    "neutral_chort",
    "neutral_ciri",
    "neutral_cow",
    "neutral_dandelion",
    "neutral_emiel",
    "neutral_gaunter_odimm",
    "neutral_gaunter_odimm_darkness",
    "neutral_gaunter_odimm_darkness",
    "neutral_gaunter_odimm_darkness",
    "monsters_arachas_1",
    "monsters_arachas_2",
    "monsters_arachas_behemoth",
    "monsters_vampire_bruxa",
    "monsters_celaeno_harpy",
    "monsters_cockatrice",
    "monsters_draug",
    "monsters_earth_elemental",
    "monsters_vampire_ekkimara",
    "monsters_endrega",
    "monsters_fiend",
    "monsters_fire_elemental",
    "monsters_vampire_fleder",
    "monsters_foglet",
    "monsters_forktail",
    "monsters_ice_giant",
    "monsters_frightener",
    "monsters_gargoyle",
    "monsters_ghoul",
    "monsters_vampire_garkain",
    "monsters_ghoul_1",
    "monsters_ghoul_2",
    "monsters_gravehag",
    "monsters_gryffin",
    "monsters_harpy",
    "monsters_imlerith",
    "monsters_vampire_katakan"
  ]
}