{
  "player1": "ali123",
  "player1Faction": "Monsters",
  "player1Hand": [
    {
      "name": "neutral_yennefer",
      "id": 115
    },
    {
      "name": "special_mardroeme_1",
      "id": 99
    },
    {
      "name": "weather_fog_1",
      "id": 101
    },
    {
      "name": "weather_frost_1",
      "id": 103
    },
    {
      "name": "weather_rain_1",
      "id": 105
    },
    {
      "name": "weather_clear_1",
      "id": 107
    },
    {
      "name": "neutral_geralt",
      "id": 109
    },
    {
      "name": "neutral_olgierd",
      "id": 111
    },
    {
      "name": "neutral_triss",
      "id": 113
    },
    {
      "name": "neutral_zoltan",
      "id": 116
    }
  ],
  "player1Deck": [
    {
      "name": "weather_fog",
      "id": 100
    },
    {
      "name": "weather_frost",
      "id": 102
    },
    {
      "name": "weather_rain",
      "id": 104
    },
    {
      "name": "weather_clear",
      "id": 106
    },
    {
      "name": "weather_storm",
      "id": 108
    },
    {
      "name": "neutral_mysterious_elf",
      "id": 110
    },
    {
      "name": "neutral_vesemir",
      "id": 112
    },
    {
      "name": "neutral_villen",
      "id": 114
    },
    {
      "name": "monsters_arachas",
      "id": 117
    },
    {
      "name": "monsters_arachas_1",
      "id": 118
    },
    {
      "name": "monsters_arachas_2",
      "id": 119
    },
    {
      "name": "monsters_arachas_behemoth",
      "id": 120
    },
    {
      "name": "monsters_vampire_bruxa",
      "id": 121
    },
    {
      "name": "monsters_celaeno_harpy",
      "id": 122
    },
    {
      "name": "monsters_cockatrice",
      "id": 123
    },
    {
      "name": "monsters_draug",
      "id": 124
    },
    {
      "name": "monsters_earth_elemental",
      "id": 125
    }
  ],
  "player2": "ali",
  "player2Faction": "Monsters",
  "player2Hand": [
    {
      "name": "neutral_yennefer",
      "id": 212
    },
    {
      "name": "neutral_cow",
      "id": 199
    },
    {
      "name": "neutral_emiel",
      "id": 201
    },
    {
      "name": "neutral_gaunter_odimm_darkness",
      "id": 203
    },
    {
      "name": "neutral_gaunter_odimm_darkness",
      "id": 205
    },
    {
      "name": "neutral_mysterious_elf",
      "id": 207
    },
    {
      "name": "neutral_triss",
      "id": 209
    },
    {
      "name": "neutral_villen",
      "id": 211
    },
    {
      "name": "monsters_arachas",
      "id": 214
    },
    {
      "name": "monsters_arachas_2",
      "id": 216
    }
  ],
  "player2Deck": [
    {
      "name": "neutral_dandelion",
      "id": 200
    },
    {
      "name": "neutral_gaunter_odimm",
      "id": 202
    },
    {
      "name": "neutral_gaunter_odimm_darkness",
      "id": 204
    },
    {
      "name": "neutral_geralt",
      "id": 206
    },
    {
      "name": "neutral_olgierd",
      "id": 208
    },
    {
      "name": "neutral_vesemir",
      "id": 210
    },
    {
      "name": "neutral_zoltan",
      "id": 213
    },
    {
      "name": "monsters_arachas_1",
      "id": 215
    },
    {
      "name": "monsters_arachas_behemoth",
      "id": 217
    },
    {
      "name": "monsters_vampire_bruxa",
      "id": 218
    },
    {
      "name": "monsters_celaeno_harpy",
      "id": 219
    },
    {
      "name": "monsters_draug",
      "id": 220
    },
    {
      "name": "monsters_earth_elemental",
      "id": 221
    }
  ],
  "commands": [
    "card with id: 109 moved from currentPlayerHand to currentPlayerCloseCombat and ability applied",
    "change turn",
    "card with id: 205 moved from currentPlayerHand to currentPlayerRanged and ability applied",
    "change turn",
    "card with id: 203 moved from currentPlayerHand to currentPlayerRanged and ability applied",
    "card with id: 204 moved from currentPlayerHand to currentPlayerRanged and ability applied",
    "card with id: 99 moved from currentPlayerHand to currentPlayerCloseCombatSpecialPlace and ability applied",
    "change turn",
    "card with id: 201 moved from currentPlayerHand to currentPlayerCloseCombat and ability applied",
    "change turn",
    "card with id: 103 moved from currentPlayerHand to weather and ability applied",
    "change turn",
    "card with id: 207 moved from currentPlayerHand to opponentCloseCombat and ability applied",
    "change turn"
  ]
}